NumNeighbours/__init__.py
NumNeighbours/main.py
NumNeighbors-0.1.0.dist-info/METADATA
NumNeighbors-0.1.0.dist-info/WHEEL
NumNeighbors-0.1.0.dist-info/top_level.txt
NumNeighbors-0.1.0.dist-info/RECORD
