Metadata-Version: 2.1
Name: NumNeighbors
Version: 0.1.0
Summary: A package to display predefined programs
Author: AJ
Author-email: shredder1142110@gmail.com
Classifier: Programming Language :: Python :: 3
Classifier: License :: OSI Approved :: MIT License
Classifier: Operating System :: OS Independent
Requires-Python: >=3.6
